pyarrow/bigquery/__init__.py
pyarrow/bigquery/read.py
pyarrow/bigquery/some_itertools.py
pyarrow/bigquery/exchange/__init__.py
pyarrow/bigquery/exchange/feather.py
pyarrow/bigquery/exchange/memory.py
pyarrow/bigquery/exchange/shared_memory.py
pyarrow/bigquery/write/__init__.py
pyarrow/bigquery/write/pa_to_bq.py
pyarrow/bigquery/write/pa_to_pb.py
pyarrow/bigquery/write/type_mapping.py
pyarrow/bigquery/write/upload.py
pyarrow_bigquery-0.5.7.dist-info/METADATA
pyarrow_bigquery-0.5.7.dist-info/WHEEL
pyarrow_bigquery-0.5.7.dist-info/top_level.txt
pyarrow_bigquery-0.5.7.dist-info/RECORD
