Metadata-Version: 2.4
Name: pyarrow-bigquery
Version: 0.5.7
Summary: An extension library to write to and read from BigQuery tables as PyArrow tables.
Author: Sebastian Pawluś
License: MIT
Keywords: pyarrow,bigquery
Requires-Python: <3.13,>=3.10
Requires-Dist: google-cloud-bigquery<5,>=3
Requires-Dist: google-cloud-bigquery-storage<3,>=2
Requires-Dist: pyarrow<20,>=16
Requires-Dist: tenacity
